mktmp/__init__.py
mktmp/cli.py
mktmp/config.py
mktmp/config_cli.py
mktmp/schema.py
mktmp-0.2.1.dist-info/METADATA
mktmp-0.2.1.dist-info/WHEEL
mktmp-0.2.1.dist-info/entry_points.txt
mktmp-0.2.1.dist-info/licenses/LICENSE
mktmp-0.2.1.dist-info/RECORD
