Metadata-Version: 2.4
Name: mktmp
Version: 0.2.1
Summary: command-line tool for creating temporary directories along with symbolic links to them
Project-URL: Homepage, https://github.com/y-guang/mktmp
Project-URL: Repository, https://github.com/y-guang/mktmp
Project-URL: Issues, https://github.com/y-guang/mktmp/issues
Project-URL: Changelog, https://github.com/y-guang/mktmp/blob/main/CHANGELOG.md
Author-email: Guang Yang <guang.spike.yang@gmail.com>
License-Expression: MIT
License-File: LICENSE
Classifier: Development Status :: 3 - Alpha
Classifier: Intended Audience :: Developers
Classifier: License :: OSI Approved :: MIT License
Classifier: Operating System :: OS Independent
Classifier: Programming Language :: Python :: 3
Classifier: Programming Language :: Python :: 3.12
Classifier: Topic :: System :: Filesystems
Classifier: Topic :: Utilities
Requires-Python: >=3.12
Requires-Dist: pydantic>=2.11.7
Requires-Dist: typer>=0.16.0
